[
  {
    "센터/부": "Biz기술본부",
    "DB관리": null,
    "공통업무": 11476.3,
    "관로 PM": null,
    "기본업무": 40847.5,
    "설비이전/관로": null,
    "순회점검": null,
    "운용 설계": null,
    "원인자 설계": null,
    "유지보수": null,
    "인프라 시설공급": null,
    "자산관리": null,
    "지원": null,
    "케이블 PM": null,
    "투자 설계": null
  },
  {
    "센터/부": "인프라설계본부",
    "DB관리": 11249.0,
    "공통업무": null,
    "관로 PM": 1525.5,
    "기본업무": null,
    "설비이전/관로": null,
    "순회점검": null,
    "운용 설계": 13586.5,
    "원인자 설계": 4355.5,
    "유지보수": null,
    "인프라 시설공급": null,
    "자산관리": 317.5,
    "지원": 1858.5,
    "케이블 PM": 4002.5,
    "투자 설계": 12499.5
  }
]